example_plugin/__init__.py
example_plugin/_dock_widget.py
example_plugin/_function.py
example_plugin/_reader.py
example_plugin/_version.py
example_plugin/_writer.py
example_plugin/_tests/__init__.py
example_plugin/_tests/test_dock_widget.py
example_plugin/_tests/test_function.py
example_plugin/_tests/test_reader.py
example_plugin/_tests/test_writer.py
example_plugin-0.0.7.dist-info/LICENSE
example_plugin-0.0.7.dist-info/METADATA
example_plugin-0.0.7.dist-info/WHEEL
example_plugin-0.0.7.dist-info/entry_points.txt
example_plugin-0.0.7.dist-info/top_level.txt
example_plugin-0.0.7.dist-info/RECORD
