Metadata-Version: 2.1
Name: example-plugin
Version: 0.0.7
Summary: An example plugin for demo purposes
Home-page: https://github.com/DragaDoncila/example-plugin
Author: Draga Doncila Pop
Author-email: ddoncila@gmail.com
License: BSD-3
Platform: UNKNOWN
Classifier: Development Status :: 2 - Pre-Alpha
Classifier: Intended Audience :: Developers
Classifier: Framework :: napari
Classifier: Topic :: Software Development :: Testing
Classifier: Programming Language :: Python
Classifier: Programming Language :: Python :: 3
Classifier: Programming Language :: Python :: 3.7
Classifier: Programming Language :: Python :: 3.8
Classifier: Programming Language :: Python :: 3.9
Classifier: Operating System :: OS Independent
Classifier: License :: OSI Approved :: BSD License
Requires-Python: >=3.7
Requires-Dist: napari-plugin-engine (>=0.1.4)
Requires-Dist: numpy
Provides-Extra: dev
Requires-Dist: pytest ; extra == 'dev'
